asyncbridge/__init__.py
asyncbridge-1.0.0.dist-info/METADATA
asyncbridge-1.0.0.dist-info/WHEEL
asyncbridge-1.0.0.dist-info/RECORD
