Metadata-Version: 2.4
Name: asyncbridge
Version: 1.0.0
Summary: Simple, reliable async/sync conversion for Python. Call async from sync and vice versa.
Project-URL: Homepage, https://github.com/SerityOps/asyncbridge
Project-URL: Documentation, https://github.com/SerityOps/asyncbridge#readme
Project-URL: Repository, https://github.com/SerityOps/asyncbridge
Project-URL: Issues, https://github.com/SerityOps/asyncbridge/issues
Author-email: LadyCami <your-email@example.com>
License: MIT
Keywords: async,asyncio,await,bridge,converter,coroutine,sync,wrapper
Classifier: Development Status :: 5 - Production/Stable
Classifier: Framework :: AsyncIO
Classifier: Intended Audience :: Developers
Classifier: License :: OSI Approved :: MIT License
Classifier: Programming Language :: Python :: 3
Classifier: Programming Language :: Python :: 3.10
Classifier: Programming Language :: Python :: 3.11
Classifier: Programming Language :: Python :: 3.12
Classifier: Topic :: Software Development :: Libraries :: Python Modules
Classifier: Typing :: Typed
Requires-Python: >=3.10
